{
  "parent": "fruits",
  "icon": "textures/items/banana",
  "title": "香蕉",
  "pages": [
    {
      "type": "textPage",
      "content": "§l获取难度: §r§c困难 | ★★★§r\n§l获取方式: §r§c丛林野生§r\n=================\n§l种植难度: §r§c困难 | ★★★§r\n§l介绍: §r§8香蕉仅在热带丛林种植，在中海拔地区生长。§r\n§l特殊: §r§c无 §r\n=================\n§r§l收获次数: §r§c3§r\n§l凋落物物: §r§c香蕉 4-7§r\n"
    },
    {
      "type": "highlightPage",
      "subtitle": "收获",
      "content": "香蕉是一种热带水果，可直接使用，香蕉制成的食物也颇受欢迎。",
      "info": "香蕉",
      "itemData": [
        {
          "item": "cookingcraft:banana",
          "date": 0
        }
      ]
    },
    {
      "type": "textPage",
      "subtitle": "故事",
      "content": "§8你一定吃过香蕉风味的软糖，布丁和饮料。你知道这些食品里面添加的是香蕉香精，而不是真的香蕉。你也可能疑惑过，为什么香精的味道，跟真的香蕉比起来差那么远。你是对的，它们确实差太远了。其实，在某种程度上来说，这不是香精的问题，而是香蕉品种的问题。我们现在吃的香蕉，跟上世纪 50 年代时的香蕉根本不是一个品种。原来的香蕉品种遭遇了灭顶之灾，近乎灭绝。"
    }
  ]
}
